<Legislation xmlns="http://www.legislation.gov.uk/namespaces/legislation" xmlns:xsi="http://www.w3.org/2001/XMLSchema-instance" DocumentURI="http://www.legislation.gov.uk/ssi/2012/319" IdURI="http://www.legislation.gov.uk/id/ssi/2012/319" NumberOfProvisions="178" xsi:schemaLocation="http://www.legislation.gov.uk/namespaces/legislation http://www.legislation.gov.uk/schema/legislation.xsd" SchemaVersion="1.0" RestrictExtent="S" RestrictStartDate="2026-04-01"><ukm:Metadata xmlns:dc="http://purl.org/dc/elements/1.1/" xmlns:dct="http://purl.org/dc/terms/" xmlns:atom="http://www.w3.org/2005/Atom" xmlns:ukm="http://www.legislation.gov.uk/namespaces/metadata">
					<dc:identifier>http://www.legislation.gov.uk/ssi/2012/319/schedule/5/paragraph/1</dc:identifier><dc:title>The Council Tax Reduction (State Pension Credit) (Scotland) Regulations 2012</dc:title><dc:type>text</dc:type><dc:format>text/xml</dc:format><dc:language>en</dc:language><dc:publisher>Statute Law Database</dc:publisher><dc:subject scheme="SIheading">COUNCIL TAX</dc:subject><dc:modified>2026-05-22</dc:modified><dc:contributor>Expert Participation</dc:contributor><dct:valid>2026-04-01</dct:valid>
					<dc:description>These Regulations make provision for a reduction in liability for council tax (“council tax reduction”) for persons who have reached the qualifying age for state pension credit. (The Council Tax Reduction (Scotland) Regulations 2012 provides for a reduction in liability for council tax for persons who have not reached the qualifying age for state pension credit.)</dc:description>
					<atom:link rel="self" href="http://www.legislation.gov.uk/ssi/2012/319/schedule/5/paragraph/1/data.xml" type="application/xml"/><atom:link rel="http://www.legislation.gov.uk/def/navigation/resources" href="http://www.legislation.gov.uk/ssi/2012/319/resources" title="More Resources"/>

					<atom:link rel="http://www.legislation.gov.uk/def/navigation/policy-note" href="http://www.legislation.gov.uk/ssi/2012/319/policy-note" title="Policy Note"/><atom:link rel="http://www.legislation.gov.uk/def/navigation/policy-note/toc" href="http://www.legislation.gov.uk/ssi/2012/319/policy-note/contents" title="Policy Note Table of Contents"/>

					<atom:link rel="http://www.legislation.gov.uk/def/navigation/act" href="http://www.legislation.gov.uk/ssi/2012/319" title="whole act"/><atom:link rel="http://www.legislation.gov.uk/def/navigation/introduction" href="http://www.legislation.gov.uk/ssi/2012/319/introduction" title="introduction"/><atom:link rel="http://www.legislation.gov.uk/def/navigation/signature" href="http://www.legislation.gov.uk/ssi/2012/319/signature" title="signature"/><atom:link rel="http://www.legislation.gov.uk/def/navigation/note" href="http://www.legislation.gov.uk/ssi/2012/319/note" title="note"/>
					<atom:link rel="http://www.legislation.gov.uk/def/navigation/body" href="http://www.legislation.gov.uk/ssi/2012/319/body" title="body"/>
					<atom:link rel="http://www.legislation.gov.uk/def/navigation/schedules" href="http://www.legislation.gov.uk/ssi/2012/319/schedules" title="schedules"/>





					<atom:link rel="alternate" type="application/rdf+xml" href="http://www.legislation.gov.uk/ssi/2012/319/schedule/5/paragraph/1/data.rdf" title="RDF/XML"/><atom:link rel="alternate" type="application/akn+xml" href="http://www.legislation.gov.uk/ssi/2012/319/schedule/5/paragraph/1/data.akn" title="AKN"/><atom:link rel="alternate" type="application/xhtml+xml" href="http://www.legislation.gov.uk/ssi/2012/319/schedule/5/paragraph/1/data.xht" title="HTML snippet"/><atom:link rel="alternate" type="text/html" href="http://www.legislation.gov.uk/ssi/2012/319/schedule/5/paragraph/1/data.htm" title="Website (XHTML) Default View"/><atom:link rel="alternate" type="text/csv" href="http://www.legislation.gov.uk/ssi/2012/319/schedule/5/paragraph/1/data.csv" title="CSV"/><atom:link rel="alternate" type="application/pdf" href="http://www.legislation.gov.uk/ssi/2012/319/schedule/5/paragraph/1/data.pdf" title="PDF"/>
					<atom:link rel="alternate" type="application/akn+xhtml" href="http://www.legislation.gov.uk/ssi/2012/319/schedule/5/paragraph/1/data.html" title="HTML5 snippet"/>


					<atom:link rel="http://purl.org/dc/terms/tableOfContents" hreflang="en" href="http://www.legislation.gov.uk/ssi/2012/319/contents" title="Table of Contents"/>

					<atom:link rel="http://purl.org/dc/terms/replaces" href="http://www.legislation.gov.uk/ssi/2012/319/schedule/5/paragraph/1/2025-04-01" title="2025-04-01"/><atom:link rel="http://purl.org/dc/terms/hasVersion" href="http://www.legislation.gov.uk/ssi/2012/319/schedule/5/paragraph/1/made" title="made"/><atom:link rel="http://purl.org/dc/terms/hasVersion" href="http://www.legislation.gov.uk/ssi/2012/319/schedule/5/paragraph/1/2013-01-28" title="2013-01-28"/><atom:link rel="http://purl.org/dc/terms/hasVersion" href="http://www.legislation.gov.uk/ssi/2012/319/schedule/5/paragraph/1/2013-03-18" title="2013-03-18"/><atom:link rel="http://purl.org/dc/terms/hasVersion" href="http://www.legislation.gov.uk/ssi/2012/319/schedule/5/paragraph/1/2013-11-25" title="2013-11-25"/><atom:link rel="http://purl.org/dc/terms/hasVersion" href="http://www.legislation.gov.uk/ssi/2012/319/schedule/5/paragraph/1/2014-04-01" title="2014-04-01"/><atom:link rel="http://purl.org/dc/terms/hasVersion" href="http://www.legislation.gov.uk/ssi/2012/319/schedule/5/paragraph/1/2015-04-01" title="2015-04-01"/><atom:link rel="http://purl.org/dc/terms/hasVersion" href="http://www.legislation.gov.uk/ssi/2012/319/schedule/5/paragraph/1/2016-04-01" title="2016-04-01"/><atom:link rel="http://purl.org/dc/terms/hasVersion" href="http://www.legislation.gov.uk/ssi/2012/319/schedule/5/paragraph/1/2017-04-01" title="2017-04-01"/><atom:link rel="http://purl.org/dc/terms/hasVersion" href="http://www.legislation.gov.uk/ssi/2012/319/schedule/5/paragraph/1/2018-04-01" title="2018-04-01"/><atom:link rel="http://purl.org/dc/terms/hasVersion" href="http://www.legislation.gov.uk/ssi/2012/319/schedule/5/paragraph/1/2019-04-01" title="2019-04-01"/><atom:link rel="http://purl.org/dc/terms/hasVersion" href="http://www.legislation.gov.uk/ssi/2012/319/schedule/5/paragraph/1/2020-04-01" title="2020-04-01"/><atom:link rel="http://purl.org/dc/terms/hasVersion" href="http://www.legislation.gov.uk/ssi/2012/319/schedule/5/paragraph/1/2022-04-01" title="2022-04-01"/><atom:link rel="http://purl.org/dc/terms/hasVersion" href="http://www.legislation.gov.uk/ssi/2012/319/schedule/5/paragraph/1/2023-04-01" title="2023-04-01"/><atom:link rel="http://purl.org/dc/terms/hasVersion" href="http://www.legislation.gov.uk/ssi/2012/319/schedule/5/paragraph/1/2024-04-01" title="2024-04-01"/><atom:link rel="http://purl.org/dc/terms/hasVersion" href="http://www.legislation.gov.uk/ssi/2012/319/schedule/5/paragraph/1/2025-04-01" title="2025-04-01"/><atom:link rel="http://purl.org/dc/terms/hasVersion" href="http://www.legislation.gov.uk/ssi/2012/319/schedule/5/paragraph/1/2026-04-01" title="2026-04-01"/>

					<atom:link rel="up" href="http://www.legislation.gov.uk/ssi/2012/319/schedule/5" title="Schedule 5"/><atom:link rel="prev" href="http://www.legislation.gov.uk/ssi/2012/319/schedule/4/paragraph/34" title="Paragraph; Schedule 4 Paragraph 34"/><atom:link rel="prevInForce" href="http://www.legislation.gov.uk/ssi/2012/319/schedule/4/paragraph/34" title="Paragraph; Schedule 4 Paragraph 34"/><atom:link rel="next" href="http://www.legislation.gov.uk/ssi/2012/319/schedule/5/paragraph/2" title="Paragraph; Schedule 5 Paragraph 2"/><atom:link rel="nextInForce" href="http://www.legislation.gov.uk/ssi/2012/319/schedule/5/paragraph/2" title="Paragraph; Schedule 5 Paragraph 2"/>
					<ukm:SecondaryMetadata><ukm:DocumentClassification><ukm:DocumentCategory Value="secondary"/><ukm:DocumentMainType Value="ScottishStatutoryInstrument"/><ukm:DocumentStatus Value="revised"/><ukm:DocumentMinorType Value="regulation"/></ukm:DocumentClassification><ukm:Year Value="2012"/><ukm:Number Value="319"/><ukm:Made Date="2012-11-21"/><ukm:Laid Date="2012-11-23" Class="UnitedKingdomParliament"/><ukm:ComingIntoForce><ukm:DateTime Date="2013-01-28"/></ukm:ComingIntoForce><ukm:ISBN Value="9780111018507"/></ukm:SecondaryMetadata>



									<ukm:Notes><ukm:Note IdURI="http://www.legislation.gov.uk/id/ssi/2012/319/notes"/><ukm:Alternatives><ukm:Alternative URI="http://www.legislation.gov.uk/ssi/2012/319/pdfs/ssipn_20120319_en.pdf" Date="2012-11-27" Title="Policy Note" Size="15421"/></ukm:Alternatives>
								</ukm:Notes>
					<ukm:Alternatives><ukm:Alternative URI="http://www.legislation.gov.uk/ssi/2012/319/pdfs/ssi_20120319_en.pdf" Date="2012-11-27" Size="441067"/></ukm:Alternatives>

					<ukm:Statistics>
									<ukm:TotalParagraphs Value="178"/>
									<ukm:BodyParagraphs Value="77"/>
									<ukm:ScheduleParagraphs Value="101"/>
									<ukm:AttachmentParagraphs Value="0"/>
									<ukm:TotalImages Value="1"/>
								</ukm:Statistics>
				</ukm:Metadata><Secondary><Schedules RestrictStartDate="2026-04-01"><Schedule DocumentURI="http://www.legislation.gov.uk/ssi/2012/319/schedule/5" IdURI="http://www.legislation.gov.uk/id/ssi/2012/319/schedule/5" NumberOfProvisions="4" id="schedule-5" RestrictStartDate="2026-04-01"><Number>SCHEDULE 5</Number><TitleBlock><Title>Amount of alternative maximum council tax reduction</Title></TitleBlock><ScheduleBody><P1 DocumentURI="http://www.legislation.gov.uk/ssi/2012/319/schedule/5/paragraph/1" IdURI="http://www.legislation.gov.uk/id/ssi/2012/319/schedule/5/paragraph/1" id="schedule-5-paragraph-1" RestrictExtent="S" RestrictStartDate="2026-04-01"><Pnumber>1</Pnumber><P1para><Text>Subject to paragraphs 2 and 3, the alternative maximum council tax reduction in respect of a day for the purpose of regulation 56 is to be determined in accordance with the following table.</Text></P1para><Tabular Orientation="portrait"><Number>Table</Number><xhtml:table xmlns:xhtml="http://www.w3.org/1999/xhtml" cols="2"><xhtml:colgroup><xhtml:col width="50%"/><xhtml:col width="50%"/></xhtml:colgroup><xhtml:tbody><xhtml:tr><xhtml:th width="624"><Emphasis>Column (1)</Emphasis><Emphasis>Second adult</Emphasis></xhtml:th><xhtml:th width="59"><Emphasis>Column (2)</Emphasis><Emphasis>Alternative maximum council tax reduction</Emphasis></xhtml:th></xhtml:tr><xhtml:tr><xhtml:td width="624">(a) Where the second adult is, or all second adults are, in receipt of income support, income-related employment and support allowance <Addition ChangeId="key-a1" CommentaryRef="key-a1">, universal credit with no earned income,</Addition>  or state pension credit or the second adult is a person, or all second adults are persons, on an income based jobseeker's allowance <CommentaryRef Ref="M_F_5c5db892-c7ea-4207-fda0-f7f3952eb2b4"/>...;</xhtml:td><xhtml:td width="59">25 per cent of the council tax due in respect of that day;</xhtml:td></xhtml:tr><xhtml:tr><xhtml:td width="624">(b) Where the gross income of the second adult or, where there is more than one second adult, their aggregate gross income, disregarding any income of persons on income support, income-related employment and support allowance <Addition ChangeId="key-a2" CommentaryRef="key-a2">, universal credit with no earned income,</Addition> state pension credit or an income based jobseeker's allowance—</xhtml:td><xhtml:td width="59"/></xhtml:tr><xhtml:tr><xhtml:td width="624"><P3 DocumentURI="http://www.legislation.gov.uk/ssi/2012/319/schedule/5/paragraph/1/i" IdURI="http://www.legislation.gov.uk/id/ssi/2012/319/schedule/5/paragraph/1/i" id="schedule-5-paragraph-1-i"><Pnumber>i</Pnumber><P3para><Text>is less than     <Substitution ChangeId="key-a3" CommentaryRef="key-a3">£282.00</Substitution> per week;</Text></P3para></P3></xhtml:td><xhtml:td width="59">15 per cent of the council tax due in respect of that day;</xhtml:td></xhtml:tr><xhtml:tr><xhtml:td width="624"><P3 DocumentURI="http://www.legislation.gov.uk/ssi/2012/319/schedule/5/paragraph/1/ii" IdURI="http://www.legislation.gov.uk/id/ssi/2012/319/schedule/5/paragraph/1/ii" id="schedule-5-paragraph-1-ii"><Pnumber>ii</Pnumber><P3para><Text>is not less than     <Substitution ChangeId="key-a4" CommentaryRef="key-a4">£282.00</Substitution> per week but is less than <Substitution ChangeId="key-a5" CommentaryRef="key-a5">£383.00</Substitution> per week.</Text></P3para></P3></xhtml:td><xhtml:td width="59">7.5 per cent of the council tax due in respect of that day.</xhtml:td></xhtml:tr><xhtml:tr><xhtml:td width="624">(c) Where the dwelling would be wholly occupied by one or more persons to whom regulation 20(2) of the Council Tax Reduction Regulations applies but for the presence of one or more second adults who are in receipt of income support, state pension credit, an income-related employment and support allowance <Addition ChangeId="key-a6" CommentaryRef="key-a6">, universal credit with no earned income,</Addition>  or are persons on an income-based jobseeker's allowance.</xhtml:td><xhtml:td width="59">100 per cent of the council tax due in respect of that day.</xhtml:td></xhtml:tr></xhtml:tbody></xhtml:table></Tabular></P1></ScheduleBody></Schedule></Schedules></Secondary><Commentaries><Commentary id="key-a1" Type="F"><Para><Text>Words in <CitationSubRef id="cpl00aq74-00006" SectionRef="schedule-5-paragraph-1" URI="http://www.legislation.gov.uk/id/ssi/2012/319/schedule/5/paragraph/1">sch. 5 para. 1</CitationSubRef> Table inserted (1.4.2022) by <Citation URI="http://www.legislation.gov.uk/id/ssi/2022/52" id="cpl00aq74-00007" Class="ScottishStatutoryInstrument" Year="2022" Number="52" Title="The Council Tax Reduction (Scotland) Amendment Regulations 2022">The Council Tax Reduction (Scotland) Amendment Regulations 2022 (S.S.I. 2022/52)</Citation>, <CitationSubRef CitationRef="cpl00aq74-00007" id="cpl00aq74-00008" SectionRef="regulation-1-3" URI="http://www.legislation.gov.uk/id/ssi/2022/52/regulation/1/3">regs. 1(3)</CitationSubRef>, <CitationSubRef CitationRef="cpl00aq74-00007" id="cpl00aq74-00009" SectionRef="regulation-29-a" URI="http://www.legislation.gov.uk/id/ssi/2022/52/regulation/29/a" Operative="true">29(a)</CitationSubRef></Text></Para></Commentary><Commentary id="key-a2" Type="F"><Para><Text>Words in <CitationSubRef id="cpl00aq74-00015" SectionRef="schedule-5-paragraph-1" URI="http://www.legislation.gov.uk/id/ssi/2012/319/schedule/5/paragraph/1">sch. 5 para. 1</CitationSubRef> Table inserted (1.4.2022) by <Citation URI="http://www.legislation.gov.uk/id/ssi/2022/52" id="cpl00aq74-00016" Class="ScottishStatutoryInstrument" Year="2022" Number="52" Title="The Council Tax Reduction (Scotland) Amendment Regulations 2022">The Council Tax Reduction (Scotland) Amendment Regulations 2022 (S.S.I. 2022/52)</Citation>, <CitationSubRef CitationRef="cpl00aq74-00016" id="cpl00aq74-00017" SectionRef="regulation-1-3" URI="http://www.legislation.gov.uk/id/ssi/2022/52/regulation/1/3">regs. 1(3)</CitationSubRef>, <CitationSubRef CitationRef="cpl00aq74-00016" id="cpl00aq74-00018" SectionRef="regulation-29-b" URI="http://www.legislation.gov.uk/id/ssi/2022/52/regulation/29/b" Operative="true">29(b)</CitationSubRef></Text></Para></Commentary><Commentary id="key-a6" Type="F"><Para><Text>Words in <CitationSubRef id="cpl00aq74-00024" SectionRef="schedule-5-paragraph-1" URI="http://www.legislation.gov.uk/id/ssi/2012/319/schedule/5/paragraph/1">sch. 5 para. 1</CitationSubRef> Table inserted (1.4.2022) by <Citation URI="http://www.legislation.gov.uk/id/ssi/2022/52" id="cpl00aq74-00025" Class="ScottishStatutoryInstrument" Year="2022" Number="52" Title="The Council Tax Reduction (Scotland) Amendment Regulations 2022">The Council Tax Reduction (Scotland) Amendment Regulations 2022 (S.S.I. 2022/52)</Citation>, <CitationSubRef CitationRef="cpl00aq74-00025" id="cpl00aq74-00026" SectionRef="regulation-1-3" URI="http://www.legislation.gov.uk/id/ssi/2022/52/regulation/1/3">regs. 1(3)</CitationSubRef>, <CitationSubRef CitationRef="cpl00aq74-00025" id="cpl00aq74-00027" SectionRef="regulation-29-c" URI="http://www.legislation.gov.uk/id/ssi/2022/52/regulation/29/c" Operative="true">29(c)</CitationSubRef></Text></Para></Commentary><Commentary id="M_F_5c5db892-c7ea-4207-fda0-f7f3952eb2b4" Type="F"><Para><Text>Words in Sch. 5 para. 1 Table omitted (25.11.2013) by virtue of <Citation URI="http://www.legislation.gov.uk/id/ssi/2013/287" id="d15e5" Class="ScottishStatutoryInstrument" Year="2013" Number="287" Title="The Council Tax Reduction (Scotland) Amendment (No. 4) Regulations 2013">The Council Tax Reduction (Scotland) Amendment (No. 4) Regulations 2013 (S.S.I. 2013/287)</Citation>, <CitationSubRef CitationRef="d15e5" id="ccd11e20420260218115336771Z" URI="http://www.legislation.gov.uk/id/ssi/2013/287/regulation/1" SectionRef="regulation-1">regs. 1</CitationSubRef>, <CitationSubRef CitationRef="d15e5" id="ccd11e20720260218115336771Z" URI="http://www.legislation.gov.uk/id/ssi/2013/287/regulation/18" Operative="true" SectionRef="regulation-18">18</CitationSubRef></Text></Para></Commentary><Commentary id="key-a3" Type="F"><Para><Text>Sum in <CitationSubRef id="c6z270z06-00007" SectionRef="schedule-5-paragraph-1" URI="http://www.legislation.gov.uk/id/ssi/2012/319/schedule/5/paragraph/1">sch. 5 para. 1</CitationSubRef> Table  substituted (1.4.2026) by <Citation URI="http://www.legislation.gov.uk/id/ssi/2026/56" id="c6z270z06-00008" Class="ScottishStatutoryInstrument" Year="2026" Number="56" Title="The Council Tax Reduction (Miscellaneous Amendment) (Scotland) Regulations 2026">The Council Tax Reduction (Miscellaneous Amendment) (Scotland) Regulations 2026 (S.S.I. 2026/56)</Citation>, <CitationSubRef CitationRef="c6z270z06-00008" id="c6z270z06-00009" SectionRef="regulation-1" URI="http://www.legislation.gov.uk/id/ssi/2026/56/regulation/1">regs. 1</CitationSubRef>, <CitationSubRef CitationRef="c6z270z06-00008" id="c6z270z06-00010" SectionRef="regulation-7-a" URI="http://www.legislation.gov.uk/id/ssi/2026/56/regulation/7/a" Operative="true">7(a)</CitationSubRef></Text></Para></Commentary><Commentary id="key-a4" Type="F"><Para><Text>Sum in <CitationSubRef id="c6z270z06-00017" SectionRef="schedule-5-paragraph-1" URI="http://www.legislation.gov.uk/id/ssi/2012/319/schedule/5/paragraph/1">sch. 5 para. 1</CitationSubRef> Table  substituted (1.4.2026) by <Citation URI="http://www.legislation.gov.uk/id/ssi/2026/56" id="c6z270z06-00018" Class="ScottishStatutoryInstrument" Year="2026" Number="56" Title="The Council Tax Reduction (Miscellaneous Amendment) (Scotland) Regulations 2026">The Council Tax Reduction (Miscellaneous Amendment) (Scotland) Regulations 2026 (S.S.I. 2026/56)</Citation>, <CitationSubRef CitationRef="c6z270z06-00018" id="c6z270z06-00019" SectionRef="regulation-1" URI="http://www.legislation.gov.uk/id/ssi/2026/56/regulation/1">regs. 1</CitationSubRef>, <CitationSubRef CitationRef="c6z270z06-00018" id="c6z270z06-00020" SectionRef="regulation-7-b-i" URI="http://www.legislation.gov.uk/id/ssi/2026/56/regulation/7/b/i" Operative="true">7(b)(i)</CitationSubRef></Text></Para></Commentary><Commentary id="key-a5" Type="F"><Para><Text>Sum in <CitationSubRef id="c6z270z06-00027" SectionRef="schedule-5-paragraph-1" URI="http://www.legislation.gov.uk/id/ssi/2012/319/schedule/5/paragraph/1">sch. 5 para. 1</CitationSubRef> Table  substituted (1.4.2026) by <Citation URI="http://www.legislation.gov.uk/id/ssi/2026/56" id="c6z270z06-00028" Class="ScottishStatutoryInstrument" Year="2026" Number="56" Title="The Council Tax Reduction (Miscellaneous Amendment) (Scotland) Regulations 2026">The Council Tax Reduction (Miscellaneous Amendment) (Scotland) Regulations 2026 (S.S.I. 2026/56)</Citation>, <CitationSubRef CitationRef="c6z270z06-00028" id="c6z270z06-00029" SectionRef="regulation-1" URI="http://www.legislation.gov.uk/id/ssi/2026/56/regulation/1">regs. 1</CitationSubRef>, <CitationSubRef CitationRef="c6z270z06-00028" id="c6z270z06-00030" SectionRef="regulation-7-b-ii" URI="http://www.legislation.gov.uk/id/ssi/2026/56/regulation/7/b/ii" Operative="true">7(b)(ii)</CitationSubRef></Text></Para></Commentary></Commentaries></Legislation>