{
  "document_class": "statute",
  "items": [
    {
      "citation_path": "us/statute/42",
      "metadata": {
        "created_date": "2026-04-17",
        "heading": "Entitlement to hospital insurance benefits",
        "identifier": "/us/usc/t42/s426",
        "kind": "section",
        "parent_citation_path": "us/statute/42",
        "publication_name": "Online@119-99",
        "references_to": [
          "us/statute/1/106",
          "us/statute/42/1382",
          "us/statute/42/1382e",
          "us/statute/42/1395",
          "us/statute/42/1395c",
          "us/statute/42/1395d",
          "us/statute/42/1395f",
          "us/statute/42/1395p",
          "us/statute/42/1395rr",
          "us/statute/42/1395x",
          "us/statute/42/401",
          "us/statute/42/402",
          "us/statute/42/410",
          "us/statute/42/414",
          "us/statute/42/422",
          "us/statute/42/423",
          "us/statute/42/425",
          "us/statute/42/426",
          "us/statute/42/426a",
          "us/statute/42/426\u20131",
          "us/statute/42/430",
          "us/statute/45/228c",
          "us/statute/45/228e",
          "us/statute/45/231f"
        ],
        "section": "426",
        "source_download_url": "https://uscode.house.gov/download/releasepoints/us/pl/119/99/xml_usc42@119-99.zip",
        "title": "42",
        "title_heading": "THE PUBLIC HEALTH AND WELFARE"
      },
      "sha256": "bcb75f33c3f9720b9d2f26d9bf0c0524cac53d2672a168a5465df49f1460075b",
      "source_format": "uslm-xml",
      "source_path": "sources/us/statute/2026-06-23-medicare-426-title-42-r2026-07-15-self-contained/uslm/usc42.xml",
      "source_url": "https://uscode.house.gov/view.xhtml?req=granuleid:USC-prelim-title42-section426&num=0&edition=prelim"
    },
    {
      "citation_path": "us/statute/42/426",
      "metadata": {
        "created_date": "2026-04-17",
        "heading": "Entitlement to hospital insurance benefits",
        "identifier": "/us/usc/t42/s426",
        "kind": "section",
        "parent_citation_path": "us/statute/42",
        "publication_name": "Online@119-99",
        "references_to": [
          "us/statute/1/106",
          "us/statute/42/1382",
          "us/statute/42/1382e",
          "us/statute/42/1395",
          "us/statute/42/1395c",
          "us/statute/42/1395d",
          "us/statute/42/1395f",
          "us/statute/42/1395p",
          "us/statute/42/1395rr",
          "us/statute/42/1395x",
          "us/statute/42/401",
          "us/statute/42/402",
          "us/statute/42/410",
          "us/statute/42/414",
          "us/statute/42/422",
          "us/statute/42/423",
          "us/statute/42/425",
          "us/statute/42/426",
          "us/statute/42/426a",
          "us/statute/42/426\u20131",
          "us/statute/42/430",
          "us/statute/45/228c",
          "us/statute/45/228e",
          "us/statute/45/231f"
        ],
        "section": "426",
        "source_download_url": "https://uscode.house.gov/download/releasepoints/us/pl/119/99/xml_usc42@119-99.zip",
        "title": "42",
        "title_heading": "THE PUBLIC HEALTH AND WELFARE"
      },
      "sha256": "bcb75f33c3f9720b9d2f26d9bf0c0524cac53d2672a168a5465df49f1460075b",
      "source_format": "uslm-xml",
      "source_path": "sources/us/statute/2026-06-23-medicare-426-title-42-r2026-07-15-self-contained/uslm/usc42.xml",
      "source_url": "https://uscode.house.gov/view.xhtml?req=granuleid:USC-prelim-title42-section426&num=0&edition=prelim"
    },
    {
      "citation_path": "us/statute/42/426/a",
      "metadata": {
        "created_date": "2026-04-17",
        "heading": "Individuals over 65 years",
        "identifier": "/us/usc/t42/s426/a",
        "kind": "subsection",
        "parent_citation_path": "us/statute/42/426",
        "publication_name": "Online@119-99",
        "references_to": [
          "us/statute/42/402",
          "us/statute/42/410"
        ],
        "section": "426",
        "section_heading": "Entitlement to hospital insurance benefits",
        "source_download_url": "https://uscode.house.gov/download/releasepoints/us/pl/119/99/xml_usc42@119-99.zip",
        "subsection": "a",
        "title": "42",
        "title_heading": "THE PUBLIC HEALTH AND WELFARE"
      },
      "sha256": "bcb75f33c3f9720b9d2f26d9bf0c0524cac53d2672a168a5465df49f1460075b",
      "source_format": "uslm-xml",
      "source_path": "sources/us/statute/2026-06-23-medicare-426-title-42-r2026-07-15-self-contained/uslm/usc42.xml",
      "source_url": "https://uscode.house.gov/view.xhtml?req=granuleid:USC-prelim-title42-section426&num=0&edition=prelim"
    },
    {
      "citation_path": "us/statute/42/426/b",
      "metadata": {
        "created_date": "2026-04-17",
        "heading": "Individuals under 65 years",
        "identifier": "/us/usc/t42/s426/b",
        "kind": "subsection",
        "parent_citation_path": "us/statute/42/426",
        "publication_name": "Online@119-99",
        "references_to": [
          "us/statute/42/402",
          "us/statute/42/410",
          "us/statute/42/422",
          "us/statute/42/423",
          "us/statute/45/231f"
        ],
        "section": "426",
        "section_heading": "Entitlement to hospital insurance benefits",
        "source_download_url": "https://uscode.house.gov/download/releasepoints/us/pl/119/99/xml_usc42@119-99.zip",
        "subsection": "b",
        "title": "42",
        "title_heading": "THE PUBLIC HEALTH AND WELFARE"
      },
      "sha256": "bcb75f33c3f9720b9d2f26d9bf0c0524cac53d2672a168a5465df49f1460075b",
      "source_format": "uslm-xml",
      "source_path": "sources/us/statute/2026-06-23-medicare-426-title-42-r2026-07-15-self-contained/uslm/usc42.xml",
      "source_url": "https://uscode.house.gov/view.xhtml?req=granuleid:USC-prelim-title42-section426&num=0&edition=prelim"
    },
    {
      "citation_path": "us/statute/42/426/c",
      "metadata": {
        "created_date": "2026-04-17",
        "heading": "Conditions",
        "identifier": "/us/usc/t42/s426/c",
        "kind": "subsection",
        "parent_citation_path": "us/statute/42/426",
        "publication_name": "Online@119-99",
        "references_to": [
          "us/statute/42/1395f",
          "us/statute/42/423"
        ],
        "section": "426",
        "section_heading": "Entitlement to hospital insurance benefits",
        "source_download_url": "https://uscode.house.gov/download/releasepoints/us/pl/119/99/xml_usc42@119-99.zip",
        "subsection": "c",
        "title": "42",
        "title_heading": "THE PUBLIC HEALTH AND WELFARE"
      },
      "sha256": "bcb75f33c3f9720b9d2f26d9bf0c0524cac53d2672a168a5465df49f1460075b",
      "source_format": "uslm-xml",
      "source_path": "sources/us/statute/2026-06-23-medicare-426-title-42-r2026-07-15-self-contained/uslm/usc42.xml",
      "source_url": "https://uscode.house.gov/view.xhtml?req=granuleid:USC-prelim-title42-section426&num=0&edition=prelim"
    },
    {
      "citation_path": "us/statute/42/426/d",
      "metadata": {
        "created_date": "2026-04-17",
        "heading": "\u201cQualified railroad retirement beneficiary\u201d defined",
        "identifier": "/us/usc/t42/s426/d",
        "kind": "subsection",
        "parent_citation_path": "us/statute/42/426",
        "publication_name": "Online@119-99",
        "references_to": [
          "us/statute/45/231f"
        ],
        "section": "426",
        "section_heading": "Entitlement to hospital insurance benefits",
        "source_download_url": "https://uscode.house.gov/download/releasepoints/us/pl/119/99/xml_usc42@119-99.zip",
        "subsection": "d",
        "title": "42",
        "title_heading": "THE PUBLIC HEALTH AND WELFARE"
      },
      "sha256": "bcb75f33c3f9720b9d2f26d9bf0c0524cac53d2672a168a5465df49f1460075b",
      "source_format": "uslm-xml",
      "source_path": "sources/us/statute/2026-06-23-medicare-426-title-42-r2026-07-15-self-contained/uslm/usc42.xml",
      "source_url": "https://uscode.house.gov/view.xhtml?req=granuleid:USC-prelim-title42-section426&num=0&edition=prelim"
    },
    {
      "citation_path": "us/statute/42/426/e",
      "metadata": {
        "created_date": "2026-04-17",
        "heading": "Benefits for widows and widowers",
        "identifier": "/us/usc/t42/s426/e",
        "kind": "subsection",
        "parent_citation_path": "us/statute/42/426",
        "publication_name": "Online@119-99",
        "references_to": [
          "us/statute/42/1382e",
          "us/statute/42/402"
        ],
        "section": "426",
        "section_heading": "Entitlement to hospital insurance benefits",
        "source_download_url": "https://uscode.house.gov/download/releasepoints/us/pl/119/99/xml_usc42@119-99.zip",
        "subsection": "e",
        "title": "42",
        "title_heading": "THE PUBLIC HEALTH AND WELFARE"
      },
      "sha256": "bcb75f33c3f9720b9d2f26d9bf0c0524cac53d2672a168a5465df49f1460075b",
      "source_format": "uslm-xml",
      "source_path": "sources/us/statute/2026-06-23-medicare-426-title-42-r2026-07-15-self-contained/uslm/usc42.xml",
      "source_url": "https://uscode.house.gov/view.xhtml?req=granuleid:USC-prelim-title42-section426&num=0&edition=prelim"
    },
    {
      "citation_path": "us/statute/42/426/f",
      "metadata": {
        "created_date": "2026-04-17",
        "heading": "Medicare waiting period for recipients of disability benefits",
        "identifier": "/us/usc/t42/s426/f",
        "kind": "subsection",
        "parent_citation_path": "us/statute/42/426",
        "publication_name": "Online@119-99",
        "references_to": [
          "us/statute/42/1395p",
          "us/statute/45/231f"
        ],
        "section": "426",
        "section_heading": "Entitlement to hospital insurance benefits",
        "source_download_url": "https://uscode.house.gov/download/releasepoints/us/pl/119/99/xml_usc42@119-99.zip",
        "subsection": "f",
        "title": "42",
        "title_heading": "THE PUBLIC HEALTH AND WELFARE"
      },
      "sha256": "bcb75f33c3f9720b9d2f26d9bf0c0524cac53d2672a168a5465df49f1460075b",
      "source_format": "uslm-xml",
      "source_path": "sources/us/statute/2026-06-23-medicare-426-title-42-r2026-07-15-self-contained/uslm/usc42.xml",
      "source_url": "https://uscode.house.gov/view.xhtml?req=granuleid:USC-prelim-title42-section426&num=0&edition=prelim"
    },
    {
      "citation_path": "us/statute/42/426/g",
      "metadata": {
        "created_date": "2026-04-17",
        "heading": "Information regarding eligibility of Federal employees",
        "identifier": "/us/usc/t42/s426/g",
        "kind": "subsection",
        "parent_citation_path": "us/statute/42/426",
        "publication_name": "Online@119-99",
        "references_to": [
          "us/statute/42/410"
        ],
        "section": "426",
        "section_heading": "Entitlement to hospital insurance benefits",
        "source_download_url": "https://uscode.house.gov/download/releasepoints/us/pl/119/99/xml_usc42@119-99.zip",
        "subsection": "g",
        "title": "42",
        "title_heading": "THE PUBLIC HEALTH AND WELFARE"
      },
      "sha256": "bcb75f33c3f9720b9d2f26d9bf0c0524cac53d2672a168a5465df49f1460075b",
      "source_format": "uslm-xml",
      "source_path": "sources/us/statute/2026-06-23-medicare-426-title-42-r2026-07-15-self-contained/uslm/usc42.xml",
      "source_url": "https://uscode.house.gov/view.xhtml?req=granuleid:USC-prelim-title42-section426&num=0&edition=prelim"
    },
    {
      "citation_path": "us/statute/42/426/h",
      "metadata": {
        "created_date": "2026-04-17",
        "heading": "Waiver of waiting period for individuals with ALS",
        "identifier": "/us/usc/t42/s426/h",
        "kind": "subsection",
        "parent_citation_path": "us/statute/42/426",
        "publication_name": "Online@119-99",
        "references_to": [],
        "section": "426",
        "section_heading": "Entitlement to hospital insurance benefits",
        "source_download_url": "https://uscode.house.gov/download/releasepoints/us/pl/119/99/xml_usc42@119-99.zip",
        "subsection": "h",
        "title": "42",
        "title_heading": "THE PUBLIC HEALTH AND WELFARE"
      },
      "sha256": "bcb75f33c3f9720b9d2f26d9bf0c0524cac53d2672a168a5465df49f1460075b",
      "source_format": "uslm-xml",
      "source_path": "sources/us/statute/2026-06-23-medicare-426-title-42-r2026-07-15-self-contained/uslm/usc42.xml",
      "source_url": "https://uscode.house.gov/view.xhtml?req=granuleid:USC-prelim-title42-section426&num=0&edition=prelim"
    },
    {
      "citation_path": "us/statute/42/426/i",
      "metadata": {
        "created_date": "2026-04-17",
        "heading": "Certain uninsured individuals",
        "identifier": "/us/usc/t42/s426/i",
        "kind": "subsection",
        "parent_citation_path": "us/statute/42/426",
        "publication_name": "Online@119-99",
        "references_to": [
          "us/statute/42/426a"
        ],
        "section": "426",
        "section_heading": "Entitlement to hospital insurance benefits",
        "source_download_url": "https://uscode.house.gov/download/releasepoints/us/pl/119/99/xml_usc42@119-99.zip",
        "subsection": "i",
        "title": "42",
        "title_heading": "THE PUBLIC HEALTH AND WELFARE"
      },
      "sha256": "bcb75f33c3f9720b9d2f26d9bf0c0524cac53d2672a168a5465df49f1460075b",
      "source_format": "uslm-xml",
      "source_path": "sources/us/statute/2026-06-23-medicare-426-title-42-r2026-07-15-self-contained/uslm/usc42.xml",
      "source_url": "https://uscode.house.gov/view.xhtml?req=granuleid:USC-prelim-title42-section426&num=0&edition=prelim"
    },
    {
      "citation_path": "us/statute/42/426/a/1",
      "metadata": {
        "created_date": "2026-04-17",
        "heading": null,
        "identifier": "/us/usc/t42/s426/a/1",
        "kind": "paragraph",
        "paragraph": "1",
        "parent_citation_path": "us/statute/42/426/a",
        "publication_name": "Online@119-99",
        "references_to": [],
        "section": "426",
        "section_heading": "Entitlement to hospital insurance benefits",
        "source_download_url": "https://uscode.house.gov/download/releasepoints/us/pl/119/99/xml_usc42@119-99.zip",
        "subsection": "a",
        "subsection_heading": "Individuals over 65 years",
        "title": "42",
        "title_heading": "THE PUBLIC HEALTH AND WELFARE"
      },
      "sha256": "bcb75f33c3f9720b9d2f26d9bf0c0524cac53d2672a168a5465df49f1460075b",
      "source_format": "uslm-xml",
      "source_path": "sources/us/statute/2026-06-23-medicare-426-title-42-r2026-07-15-self-contained/uslm/usc42.xml",
      "source_url": "https://uscode.house.gov/view.xhtml?req=granuleid:USC-prelim-title42-section426&num=0&edition=prelim"
    },
    {
      "citation_path": "us/statute/42/426/a/2",
      "metadata": {
        "created_date": "2026-04-17",
        "heading": null,
        "identifier": "/us/usc/t42/s426/a/2",
        "kind": "paragraph",
        "paragraph": "2",
        "parent_citation_path": "us/statute/42/426/a",
        "publication_name": "Online@119-99",
        "references_to": [
          "us/statute/42/402",
          "us/statute/42/410"
        ],
        "section": "426",
        "section_heading": "Entitlement to hospital insurance benefits",
        "source_download_url": "https://uscode.house.gov/download/releasepoints/us/pl/119/99/xml_usc42@119-99.zip",
        "subsection": "a",
        "subsection_heading": "Individuals over 65 years",
        "title": "42",
        "title_heading": "THE PUBLIC HEALTH AND WELFARE"
      },
      "sha256": "bcb75f33c3f9720b9d2f26d9bf0c0524cac53d2672a168a5465df49f1460075b",
      "source_format": "uslm-xml",
      "source_path": "sources/us/statute/2026-06-23-medicare-426-title-42-r2026-07-15-self-contained/uslm/usc42.xml",
      "source_url": "https://uscode.house.gov/view.xhtml?req=granuleid:USC-prelim-title42-section426&num=0&edition=prelim"
    },
    {
      "citation_path": "us/statute/42/426/b/1",
      "metadata": {
        "created_date": "2026-04-17",
        "heading": null,
        "identifier": "/us/usc/t42/s426/b/1",
        "kind": "paragraph",
        "paragraph": "1",
        "parent_citation_path": "us/statute/42/426/b",
        "publication_name": "Online@119-99",
        "references_to": [],
        "section": "426",
        "section_heading": "Entitlement to hospital insurance benefits",
        "source_download_url": "https://uscode.house.gov/download/releasepoints/us/pl/119/99/xml_usc42@119-99.zip",
        "subsection": "b",
        "subsection_heading": "Individuals under 65 years",
        "title": "42",
        "title_heading": "THE PUBLIC HEALTH AND WELFARE"
      },
      "sha256": "bcb75f33c3f9720b9d2f26d9bf0c0524cac53d2672a168a5465df49f1460075b",
      "source_format": "uslm-xml",
      "source_path": "sources/us/statute/2026-06-23-medicare-426-title-42-r2026-07-15-self-contained/uslm/usc42.xml",
      "source_url": "https://uscode.house.gov/view.xhtml?req=granuleid:USC-prelim-title42-section426&num=0&edition=prelim"
    },
    {
      "citation_path": "us/statute/42/426/b/2",
      "metadata": {
        "created_date": "2026-04-17",
        "heading": null,
        "identifier": "/us/usc/t42/s426/b/2",
        "kind": "paragraph",
        "paragraph": "2",
        "parent_citation_path": "us/statute/42/426/b",
        "publication_name": "Online@119-99",
        "references_to": [
          "us/statute/42/402",
          "us/statute/42/410",
          "us/statute/42/423",
          "us/statute/45/231f"
        ],
        "section": "426",
        "section_heading": "Entitlement to hospital insurance benefits",
        "source_download_url": "https://uscode.house.gov/download/releasepoints/us/pl/119/99/xml_usc42@119-99.zip",
        "subsection": "b",
        "subsection_heading": "Individuals under 65 years",
        "title": "42",
        "title_heading": "THE PUBLIC HEALTH AND WELFARE"
      },
      "sha256": "bcb75f33c3f9720b9d2f26d9bf0c0524cac53d2672a168a5465df49f1460075b",
      "source_format": "uslm-xml",
      "source_path": "sources/us/statute/2026-06-23-medicare-426-title-42-r2026-07-15-self-contained/uslm/usc42.xml",
      "source_url": "https://uscode.house.gov/view.xhtml?req=granuleid:USC-prelim-title42-section426&num=0&edition=prelim"
    },
    {
      "citation_path": "us/statute/42/426/c/1",
      "metadata": {
        "created_date": "2026-04-17",
        "heading": null,
        "identifier": "/us/usc/t42/s426/c/1",
        "kind": "paragraph",
        "paragraph": "1",
        "parent_citation_path": "us/statute/42/426/c",
        "publication_name": "Online@119-99",
        "references_to": [
          "us/statute/42/1395f"
        ],
        "section": "426",
        "section_heading": "Entitlement to hospital insurance benefits",
        "source_download_url": "https://uscode.house.gov/download/releasepoints/us/pl/119/99/xml_usc42@119-99.zip",
        "subsection": "c",
        "subsection_heading": "Conditions",
        "title": "42",
        "title_heading": "THE PUBLIC HEALTH AND WELFARE"
      },
      "sha256": "bcb75f33c3f9720b9d2f26d9bf0c0524cac53d2672a168a5465df49f1460075b",
      "source_format": "uslm-xml",
      "source_path": "sources/us/statute/2026-06-23-medicare-426-title-42-r2026-07-15-self-contained/uslm/usc42.xml",
      "source_url": "https://uscode.house.gov/view.xhtml?req=granuleid:USC-prelim-title42-section426&num=0&edition=prelim"
    },
    {
      "citation_path": "us/statute/42/426/c/2",
      "metadata": {
        "created_date": "2026-04-17",
        "heading": null,
        "identifier": "/us/usc/t42/s426/c/2",
        "kind": "paragraph",
        "paragraph": "2",
        "parent_citation_path": "us/statute/42/426/c",
        "publication_name": "Online@119-99",
        "references_to": [
          "us/statute/42/423"
        ],
        "section": "426",
        "section_heading": "Entitlement to hospital insurance benefits",
        "source_download_url": "https://uscode.house.gov/download/releasepoints/us/pl/119/99/xml_usc42@119-99.zip",
        "subsection": "c",
        "subsection_heading": "Conditions",
        "title": "42",
        "title_heading": "THE PUBLIC HEALTH AND WELFARE"
      },
      "sha256": "bcb75f33c3f9720b9d2f26d9bf0c0524cac53d2672a168a5465df49f1460075b",
      "source_format": "uslm-xml",
      "source_path": "sources/us/statute/2026-06-23-medicare-426-title-42-r2026-07-15-self-contained/uslm/usc42.xml",
      "source_url": "https://uscode.house.gov/view.xhtml?req=granuleid:USC-prelim-title42-section426&num=0&edition=prelim"
    },
    {
      "citation_path": "us/statute/42/426/e/1",
      "metadata": {
        "created_date": "2026-04-17",
        "heading": null,
        "identifier": "/us/usc/t42/s426/e/1",
        "kind": "paragraph",
        "paragraph": "1",
        "parent_citation_path": "us/statute/42/426/e",
        "publication_name": "Online@119-99",
        "references_to": [
          "us/statute/42/1382e",
          "us/statute/42/402"
        ],
        "section": "426",
        "section_heading": "Entitlement to hospital insurance benefits",
        "source_download_url": "https://uscode.house.gov/download/releasepoints/us/pl/119/99/xml_usc42@119-99.zip",
        "subsection": "e",
        "subsection_heading": "Benefits for widows and widowers",
        "title": "42",
        "title_heading": "THE PUBLIC HEALTH AND WELFARE"
      },
      "sha256": "bcb75f33c3f9720b9d2f26d9bf0c0524cac53d2672a168a5465df49f1460075b",
      "source_format": "uslm-xml",
      "source_path": "sources/us/statute/2026-06-23-medicare-426-title-42-r2026-07-15-self-contained/uslm/usc42.xml",
      "source_url": "https://uscode.house.gov/view.xhtml?req=granuleid:USC-prelim-title42-section426&num=0&edition=prelim"
    },
    {
      "citation_path": "us/statute/42/426/e/2",
      "metadata": {
        "created_date": "2026-04-17",
        "heading": null,
        "identifier": "/us/usc/t42/s426/e/2",
        "kind": "paragraph",
        "paragraph": "2",
        "parent_citation_path": "us/statute/42/426/e",
        "publication_name": "Online@119-99",
        "references_to": [
          "us/statute/42/402"
        ],
        "section": "426",
        "section_heading": "Entitlement to hospital insurance benefits",
        "source_download_url": "https://uscode.house.gov/download/releasepoints/us/pl/119/99/xml_usc42@119-99.zip",
        "subsection": "e",
        "subsection_heading": "Benefits for widows and widowers",
        "title": "42",
        "title_heading": "THE PUBLIC HEALTH AND WELFARE"
      },
      "sha256": "bcb75f33c3f9720b9d2f26d9bf0c0524cac53d2672a168a5465df49f1460075b",
      "source_format": "uslm-xml",
      "source_path": "sources/us/statute/2026-06-23-medicare-426-title-42-r2026-07-15-self-contained/uslm/usc42.xml",
      "source_url": "https://uscode.house.gov/view.xhtml?req=granuleid:USC-prelim-title42-section426&num=0&edition=prelim"
    },
    {
      "citation_path": "us/statute/42/426/e/3",
      "metadata": {
        "created_date": "2026-04-17",
        "heading": null,
        "identifier": "/us/usc/t42/s426/e/3",
        "kind": "paragraph",
        "paragraph": "3",
        "parent_citation_path": "us/statute/42/426/e",
        "publication_name": "Online@119-99",
        "references_to": [],
        "section": "426",
        "section_heading": "Entitlement to hospital insurance benefits",
        "source_download_url": "https://uscode.house.gov/download/releasepoints/us/pl/119/99/xml_usc42@119-99.zip",
        "subsection": "e",
        "subsection_heading": "Benefits for widows and widowers",
        "title": "42",
        "title_heading": "THE PUBLIC HEALTH AND WELFARE"
      },
      "sha256": "bcb75f33c3f9720b9d2f26d9bf0c0524cac53d2672a168a5465df49f1460075b",
      "source_format": "uslm-xml",
      "source_path": "sources/us/statute/2026-06-23-medicare-426-title-42-r2026-07-15-self-contained/uslm/usc42.xml",
      "source_url": "https://uscode.house.gov/view.xhtml?req=granuleid:USC-prelim-title42-section426&num=0&edition=prelim"
    },
    {
      "citation_path": "us/statute/42/426/e/4",
      "metadata": {
        "created_date": "2026-04-17",
        "heading": null,
        "identifier": "/us/usc/t42/s426/e/4",
        "kind": "paragraph",
        "paragraph": "4",
        "parent_citation_path": "us/statute/42/426/e",
        "publication_name": "Online@119-99",
        "references_to": [
          "us/statute/42/402"
        ],
        "section": "426",
        "section_heading": "Entitlement to hospital insurance benefits",
        "source_download_url": "https://uscode.house.gov/download/releasepoints/us/pl/119/99/xml_usc42@119-99.zip",
        "subsection": "e",
        "subsection_heading": "Benefits for widows and widowers",
        "title": "42",
        "title_heading": "THE PUBLIC HEALTH AND WELFARE"
      },
      "sha256": "bcb75f33c3f9720b9d2f26d9bf0c0524cac53d2672a168a5465df49f1460075b",
      "source_format": "uslm-xml",
      "source_path": "sources/us/statute/2026-06-23-medicare-426-title-42-r2026-07-15-self-contained/uslm/usc42.xml",
      "source_url": "https://uscode.house.gov/view.xhtml?req=granuleid:USC-prelim-title42-section426&num=0&edition=prelim"
    },
    {
      "citation_path": "us/statute/42/426/f/1",
      "metadata": {
        "created_date": "2026-04-17",
        "heading": null,
        "identifier": "/us/usc/t42/s426/f/1",
        "kind": "paragraph",
        "paragraph": "1",
        "parent_citation_path": "us/statute/42/426/f",
        "publication_name": "Online@119-99",
        "references_to": [],
        "section": "426",
        "section_heading": "Entitlement to hospital insurance benefits",
        "source_download_url": "https://uscode.house.gov/download/releasepoints/us/pl/119/99/xml_usc42@119-99.zip",
        "subsection": "f",
        "subsection_heading": "Medicare waiting period for recipients of disability benefits",
        "title": "42",
        "title_heading": "THE PUBLIC HEALTH AND WELFARE"
      },
      "sha256": "bcb75f33c3f9720b9d2f26d9bf0c0524cac53d2672a168a5465df49f1460075b",
      "source_format": "uslm-xml",
      "source_path": "sources/us/statute/2026-06-23-medicare-426-title-42-r2026-07-15-self-contained/uslm/usc42.xml",
      "source_url": "https://uscode.house.gov/view.xhtml?req=granuleid:USC-prelim-title42-section426&num=0&edition=prelim"
    },
    {
      "citation_path": "us/statute/42/426/f/2",
      "metadata": {
        "created_date": "2026-04-17",
        "heading": null,
        "identifier": "/us/usc/t42/s426/f/2",
        "kind": "paragraph",
        "paragraph": "2",
        "parent_citation_path": "us/statute/42/426/f",
        "publication_name": "Online@119-99",
        "references_to": [],
        "section": "426",
        "section_heading": "Entitlement to hospital insurance benefits",
        "source_download_url": "https://uscode.house.gov/download/releasepoints/us/pl/119/99/xml_usc42@119-99.zip",
        "subsection": "f",
        "subsection_heading": "Medicare waiting period for recipients of disability benefits",
        "title": "42",
        "title_heading": "THE PUBLIC HEALTH AND WELFARE"
      },
      "sha256": "bcb75f33c3f9720b9d2f26d9bf0c0524cac53d2672a168a5465df49f1460075b",
      "source_format": "uslm-xml",
      "source_path": "sources/us/statute/2026-06-23-medicare-426-title-42-r2026-07-15-self-contained/uslm/usc42.xml",
      "source_url": "https://uscode.house.gov/view.xhtml?req=granuleid:USC-prelim-title42-section426&num=0&edition=prelim"
    },
    {
      "citation_path": "us/statute/42/426/h/1",
      "metadata": {
        "created_date": "2026-04-17",
        "heading": null,
        "identifier": "/us/usc/t42/s426/h/1",
        "kind": "paragraph",
        "paragraph": "1",
        "parent_citation_path": "us/statute/42/426/h",
        "publication_name": "Online@119-99",
        "references_to": [],
        "section": "426",
        "section_heading": "Entitlement to hospital insurance benefits",
        "source_download_url": "https://uscode.house.gov/download/releasepoints/us/pl/119/99/xml_usc42@119-99.zip",
        "subsection": "h",
        "subsection_heading": "Waiver of waiting period for individuals with ALS",
        "title": "42",
        "title_heading": "THE PUBLIC HEALTH AND WELFARE"
      },
      "sha256": "bcb75f33c3f9720b9d2f26d9bf0c0524cac53d2672a168a5465df49f1460075b",
      "source_format": "uslm-xml",
      "source_path": "sources/us/statute/2026-06-23-medicare-426-title-42-r2026-07-15-self-contained/uslm/usc42.xml",
      "source_url": "https://uscode.house.gov/view.xhtml?req=granuleid:USC-prelim-title42-section426&num=0&edition=prelim"
    },
    {
      "citation_path": "us/statute/42/426/h/2",
      "metadata": {
        "created_date": "2026-04-17",
        "heading": null,
        "identifier": "/us/usc/t42/s426/h/2",
        "kind": "paragraph",
        "paragraph": "2",
        "parent_citation_path": "us/statute/42/426/h",
        "publication_name": "Online@119-99",
        "references_to": [],
        "section": "426",
        "section_heading": "Entitlement to hospital insurance benefits",
        "source_download_url": "https://uscode.house.gov/download/releasepoints/us/pl/119/99/xml_usc42@119-99.zip",
        "subsection": "h",
        "subsection_heading": "Waiver of waiting period for individuals with ALS",
        "title": "42",
        "title_heading": "THE PUBLIC HEALTH AND WELFARE"
      },
      "sha256": "bcb75f33c3f9720b9d2f26d9bf0c0524cac53d2672a168a5465df49f1460075b",
      "source_format": "uslm-xml",
      "source_path": "sources/us/statute/2026-06-23-medicare-426-title-42-r2026-07-15-self-contained/uslm/usc42.xml",
      "source_url": "https://uscode.house.gov/view.xhtml?req=granuleid:USC-prelim-title42-section426&num=0&edition=prelim"
    },
    {
      "citation_path": "us/statute/42/426/h/3",
      "metadata": {
        "created_date": "2026-04-17",
        "heading": null,
        "identifier": "/us/usc/t42/s426/h/3",
        "kind": "paragraph",
        "paragraph": "3",
        "parent_citation_path": "us/statute/42/426/h",
        "publication_name": "Online@119-99",
        "references_to": [],
        "section": "426",
        "section_heading": "Entitlement to hospital insurance benefits",
        "source_download_url": "https://uscode.house.gov/download/releasepoints/us/pl/119/99/xml_usc42@119-99.zip",
        "subsection": "h",
        "subsection_heading": "Waiver of waiting period for individuals with ALS",
        "title": "42",
        "title_heading": "THE PUBLIC HEALTH AND WELFARE"
      },
      "sha256": "bcb75f33c3f9720b9d2f26d9bf0c0524cac53d2672a168a5465df49f1460075b",
      "source_format": "uslm-xml",
      "source_path": "sources/us/statute/2026-06-23-medicare-426-title-42-r2026-07-15-self-contained/uslm/usc42.xml",
      "source_url": "https://uscode.house.gov/view.xhtml?req=granuleid:USC-prelim-title42-section426&num=0&edition=prelim"
    }
  ],
  "jurisdiction": "us",
  "source_count": 26,
  "version": "2026-06-23-medicare-426-title-42-r2026-07-15-self-contained"
}
