{
  "derived_from": "provisions",
  "document_class": "regulation",
  "items": [
    {
      "citation_path": "us-ny/regulation/18-nycrr/385",
      "metadata": {
        "agency": "New York State Office of Temporary and Disability Assistance",
        "derived_from": "provisions",
        "primary_source": true,
        "program": "SNAP",
        "source_id": "cornell-lii-18-nycrr-385-3",
        "source_note": "Cornell LII publication of New York regulation text, used as a corpus normalization source pending a full official NYCRR ingest.",
        "title": "Public Assistance And Food Stamp Employment Program Requirements"
      },
      "source_format": "html",
      "source_url": "https://www.law.cornell.edu/regulations/new-york/18-NYCRR-385.3"
    },
    {
      "citation_path": "us-ny/regulation/18-nycrr/387/9",
      "metadata": {
        "agency": "New York State Office of Temporary and Disability Assistance",
        "derived_from": "provisions",
        "primary_source": true,
        "program": "SNAP",
        "source_id": "cornell-lii-18-nycrr-387-9",
        "source_note": "Cornell LII publication of New York regulation text, used as a corpus normalization source pending a full official NYCRR ingest.",
        "title": "Investigation and eligibility"
      },
      "source_format": "html",
      "source_url": "https://www.law.cornell.edu/regulations/new-york/18-NYCRR-387.9"
    },
    {
      "citation_path": "us-ny/regulation/18-nycrr/387/9/a",
      "metadata": {
        "agency": "New York State Office of Temporary and Disability Assistance",
        "derived_from": "provisions",
        "primary_source": true,
        "program": "SNAP",
        "source_id": "cornell-lii-18-nycrr-387-9",
        "source_note": "Cornell LII publication of New York regulation text, used as a corpus normalization source pending a full official NYCRR ingest.",
        "title": "Nonfinancial eligibility requirements"
      },
      "source_format": "html",
      "source_url": "https://www.law.cornell.edu/regulations/new-york/18-NYCRR-387.9"
    },
    {
      "citation_path": "us-ny/regulation/18-nycrr/387/14",
      "metadata": {
        "agency": "New York State Office of Temporary and Disability Assistance",
        "derived_from": "provisions",
        "primary_source": true,
        "program": "SNAP",
        "source_id": "cornell-lii-18-nycrr-387-14",
        "source_note": "Cornell LII publication of New York regulation text, used as a corpus normalization source pending a full official NYCRR ingest.",
        "title": "Determination of Supplemental Nutrition Assistance Program (SNAP) eligibility"
      },
      "source_format": "html",
      "source_url": "https://www.law.cornell.edu/regulations/new-york/18-NYCRR-387.14"
    },
    {
      "citation_path": "us-ny/regulation/18-nycrr/387/14/a",
      "metadata": {
        "agency": "New York State Office of Temporary and Disability Assistance",
        "derived_from": "provisions",
        "primary_source": true,
        "program": "SNAP",
        "source_id": "cornell-lii-18-nycrr-387-14",
        "source_note": "Cornell LII publication of New York regulation text, used as a corpus normalization source pending a full official NYCRR ingest.",
        "title": "Application processing and categorical eligibility"
      },
      "source_format": "html",
      "source_url": "https://www.law.cornell.edu/regulations/new-york/18-NYCRR-387.14"
    },
    {
      "citation_path": "us-ny/regulation/18-nycrr/387/14/a/1",
      "metadata": {
        "agency": "New York State Office of Temporary and Disability Assistance",
        "derived_from": "provisions",
        "primary_source": true,
        "program": "SNAP",
        "source_id": "cornell-lii-18-nycrr-387-14",
        "source_note": "Cornell LII publication of New York regulation text, used as a corpus normalization source pending a full official NYCRR ingest.",
        "title": "Initial month benefit proration"
      },
      "source_format": "html",
      "source_url": "https://www.law.cornell.edu/regulations/new-york/18-NYCRR-387.14"
    },
    {
      "citation_path": "us-ny/regulation/18-nycrr/387/14/a/5",
      "metadata": {
        "agency": "New York State Office of Temporary and Disability Assistance",
        "derived_from": "provisions",
        "primary_source": true,
        "program": "SNAP",
        "source_id": "cornell-lii-18-nycrr-387-14",
        "source_note": "Cornell LII publication of New York regulation text, used as a corpus normalization source pending a full official NYCRR ingest.",
        "title": "Categorical eligibility"
      },
      "source_format": "html",
      "source_url": "https://www.law.cornell.edu/regulations/new-york/18-NYCRR-387.14"
    },
    {
      "citation_path": "us-ny/regulation/18-nycrr/387/10",
      "metadata": {
        "agency": "New York State Office of Temporary and Disability Assistance",
        "derived_from": "provisions",
        "primary_source": true,
        "program": "SNAP",
        "source_id": "cornell-lii-18-nycrr-387-10",
        "source_note": "Cornell LII publication of New York regulation text, used as a corpus normalization source pending a full official NYCRR ingest.",
        "title": "Income standards"
      },
      "source_format": "html",
      "source_url": "https://www.law.cornell.edu/regulations/new-york/18-NYCRR-387.10"
    },
    {
      "citation_path": "us-ny/regulation/18-nycrr/387/12/a",
      "metadata": {
        "agency": "New York State Office of Temporary and Disability Assistance",
        "derived_from": "provisions",
        "primary_source": true,
        "program": "SNAP",
        "source_id": "cornell-lii-18-nycrr-387-12",
        "source_note": "Cornell LII publication of New York regulation text, used as a corpus normalization source pending a full official NYCRR ingest.",
        "title": "Standard deductions"
      },
      "source_format": "html",
      "source_url": "https://www.law.cornell.edu/regulations/new-york/18-NYCRR-387.12"
    },
    {
      "citation_path": "us-ny/regulation/18-nycrr/387/12/b",
      "metadata": {
        "agency": "New York State Office of Temporary and Disability Assistance",
        "derived_from": "provisions",
        "primary_source": true,
        "program": "SNAP",
        "source_id": "cornell-lii-18-nycrr-387-12",
        "source_note": "Cornell LII publication of New York regulation text, used as a corpus normalization source pending a full official NYCRR ingest.",
        "title": "Earned income deduction"
      },
      "source_format": "html",
      "source_url": "https://www.law.cornell.edu/regulations/new-york/18-NYCRR-387.12"
    },
    {
      "citation_path": "us-ny/regulation/18-nycrr/387/12/f/3/vi",
      "metadata": {
        "agency": "New York State Office of Temporary and Disability Assistance",
        "derived_from": "provisions",
        "primary_source": true,
        "program": "SNAP",
        "source_id": "cornell-lii-18-nycrr-387-12",
        "source_note": "Cornell LII publication of New York regulation text, used as a corpus normalization source pending a full official NYCRR ingest.",
        "title": "Shelter costs for homeless households"
      },
      "source_format": "html",
      "source_url": "https://www.law.cornell.edu/regulations/new-york/18-NYCRR-387.12"
    },
    {
      "citation_path": "us-ny/regulation/18-nycrr/387/9/a/1",
      "metadata": {
        "agency": "New York State Office of Temporary and Disability Assistance",
        "derived_from": "provisions",
        "primary_source": true,
        "program": "SNAP",
        "source_id": "cornell-lii-18-nycrr-387-9",
        "source_note": "Cornell LII publication of New York regulation text, used as a corpus normalization source pending a full official NYCRR ingest.",
        "title": "Residency"
      },
      "source_format": "html",
      "source_url": "https://www.law.cornell.edu/regulations/new-york/18-NYCRR-387.9"
    },
    {
      "citation_path": "us-ny/regulation/18-nycrr/387/9/a/2",
      "metadata": {
        "agency": "New York State Office of Temporary and Disability Assistance",
        "derived_from": "provisions",
        "primary_source": true,
        "program": "SNAP",
        "source_id": "cornell-lii-18-nycrr-387-9",
        "source_note": "Cornell LII publication of New York regulation text, used as a corpus normalization source pending a full official NYCRR ingest.",
        "title": "Citizens and eligible aliens"
      },
      "source_format": "html",
      "source_url": "https://www.law.cornell.edu/regulations/new-york/18-NYCRR-387.9"
    },
    {
      "citation_path": "us-ny/regulation/18-nycrr/385/3",
      "metadata": {
        "agency": "New York State Office of Temporary and Disability Assistance",
        "derived_from": "provisions",
        "primary_source": true,
        "program": "SNAP",
        "source_id": "cornell-lii-18-nycrr-385-3",
        "source_note": "Cornell LII publication of New York regulation text, used as a corpus normalization source pending a full official NYCRR ingest.",
        "title": "Work registration and SNAP work requirements"
      },
      "source_format": "html",
      "source_url": "https://www.law.cornell.edu/regulations/new-york/18-NYCRR-385.3"
    }
  ],
  "jurisdiction": "us-ny",
  "source_count": 14,
  "version": "2026-05-09-ny-snap-eligibility"
}
